seedir/__init__.py
seedir/__main__.py
seedir/errors.py
seedir/fakedir.py
seedir/folderstructure.py
seedir/printing.py
seedir/realdir.py
seedir/words.txt
seedir-0.5.0.dist-info/LICENSE
seedir-0.5.0.dist-info/METADATA
seedir-0.5.0.dist-info/WHEEL
seedir-0.5.0.dist-info/entry_points.txt
seedir-0.5.0.dist-info/top_level.txt
seedir-0.5.0.dist-info/RECORD
