Metadata-Version: 2.1
Name: seedir
Version: 0.5.0
Summary: Package for creating, editing, and reading folder tree diagrams.
Home-page: https://github.com/earnestt1234/seedir
Author: Tom Earnest
Author-email: earnestt1234@gmail.com
License: MIT
License-File: LICENSE
Requires-Dist: natsort
Provides-Extra: emoji
Requires-Dist: emoji; extra == "emoji"
